nua/lib/__init__.py
nua/lib/actions/__init__.py
nua/lib/actions/apt.py
nua/lib/actions/constants.py
nua/lib/actions/jinja.py
nua/lib/actions/misc.py
nua/lib/actions/nodejs.py
nua/lib/actions/python.py
nua/lib/actions/ruby.py
nua/lib/actions/util.py
nua/lib/archive_search.py
nua/lib/backports.py
nua/lib/console.py
nua/lib/constants.py
nua/lib/dates.py
nua/lib/docker.py
nua/lib/elapsed.py
nua/lib/exceptions.py
nua/lib/exec.py
nua/lib/gen_password.py
nua/lib/normalization.py
nua/lib/nua_config.py
nua/lib/nua_config_format.py
nua/lib/nua_tag.py
nua/lib/panic.py
nua/lib/shell.py
nua/lib/tool/__init__.py
nua/lib/tool/color_str.py
nua/lib/tool/state.py
nua/lib/unarchiver.py
nua/lib/version.py
nua_lib-0.5.43.dist-info/METADATA
nua_lib-0.5.43.dist-info/WHEEL
nua_lib-0.5.43.dist-info/RECORD
