Metadata-Version: 2.1
Name: nua-lib
Version: 0.5.43
Summary: Nua common library
Home-page: https://github.com/abilian/nua
License: Apache-2.0
Author: Stefane Fermigier
Author-email: sf@abilian.com
Requires-Python: >=3.10,<4.0
Classifier: Development Status :: 3 - Alpha
Classifier: Environment :: Console
Classifier: Intended Audience :: Developers
Classifier: License :: OSI Approved :: Apache Software License
Classifier: Programming Language :: Python :: 3
Classifier: Programming Language :: Python :: 3.10
Classifier: Programming Language :: Python :: 3.11
Requires-Dist: dictdiffer (>=0.9.0,<0.10.0)
Requires-Dist: docker (>=6.0.1,<7.0.0)
Requires-Dist: jinja2 (>=3.1.2,<4.0.0)
Requires-Dist: pydantic (>=1.10.8,<2.0.0)
Requires-Dist: pyyaml (>=6.0,<7.0)
Requires-Dist: setuptools
Requires-Dist: tomli (>=2.0.1,<3.0.0)
Project-URL: Documentation, https://nua.rocks/
Project-URL: Repository, https://github.com/abilian/nua
